{
  "legislative_session": "2026",
  "identifier": "SB0312",
  "title": "Constitutional Officers - Salaries",
  "from_organization": "~{\"classification\": \"upper\"}",
  "classification": [
    "bill"
  ],
  "subject": [],
  "abstracts": [],
  "other_titles": [],
  "other_identifiers": [
    {
      "identifier": "ocd-bill-md-2026-sb312"
    }
  ],
  "actions": [
    {
      "description": "First Reading Budget and Taxation",
      "date": "2026-01-21",
      "organization_id": "~{\"classification\": \"upper\"}",
      "classification": [
        "referral-committee"
      ],
      "related_entities": [],
      "_processing": {
        "log_file_created": "2026-07-15T03:56:40Z"
      }
    },
    {
      "description": "Hearing 3/11 at 1:00 p.m.",
      "date": "2026-03-05",
      "organization_id": "~{\"classification\": \"upper\"}",
      "classification": [],
      "related_entities": [],
      "_processing": {
        "log_file_created": "2026-07-15T03:56:40Z"
      }
    },
    {
      "description": "Favorable Report by Budget and Taxation",
      "date": "2026-03-13",
      "organization_id": "~{\"classification\": \"upper\"}",
      "classification": [
        "committee-passage-favorable"
      ],
      "related_entities": [],
      "_processing": {
        "log_file_created": "2026-07-15T03:56:40Z"
      }
    },
    {
      "description": "Favorable Adopted",
      "date": "2026-03-13",
      "organization_id": "~{\"classification\": \"upper\"}",
      "classification": [
        "committee-passage-favorable"
      ],
      "related_entities": [],
      "_processing": {
        "log_file_created": "2026-07-15T03:56:40Z"
      }
    },
    {
      "description": "Second Reading Passed",
      "date": "2026-03-13",
      "organization_id": "~{\"classification\": \"upper\"}",
      "classification": [],
      "related_entities": [],
      "_processing": {
        "log_file_created": "2026-07-15T03:56:40Z"
      }
    },
    {
      "description": "Third Reading Passed",
      "date": "2026-03-18",
      "organization_id": "~{\"classification\": \"upper\"}",
      "classification": [
        "passage"
      ],
      "related_entities": [],
      "_processing": {
        "log_file_created": "2026-07-15T03:56:40Z"
      }
    },
    {
      "description": "Referred Appropriations",
      "date": "2026-03-18",
      "organization_id": "~{\"classification\": \"lower\"}",
      "classification": [
        "referral-committee"
      ],
      "related_entities": [],
      "_processing": {
        "log_file_created": "2026-07-15T03:56:40Z"
      }
    },
    {
      "description": "Hearing 3/25 at 1:00 p.m.",
      "date": "2026-03-21",
      "organization_id": "~{\"classification\": \"lower\"}",
      "classification": [],
      "related_entities": [],
      "_processing": {
        "log_file_created": "2026-07-15T03:56:40Z"
      }
    },
    {
      "description": "Favorable Report by Appropriations",
      "date": "2026-04-07",
      "organization_id": "~{\"classification\": \"lower\"}",
      "classification": [
        "committee-passage-favorable"
      ],
      "related_entities": [],
      "_processing": {
        "log_file_created": "2026-07-15T03:56:40Z"
      }
    },
    {
      "description": "Favorable Adopted Second Reading Passed",
      "date": "2026-04-07",
      "organization_id": "~{\"classification\": \"lower\"}",
      "classification": [
        "committee-passage-favorable"
      ],
      "related_entities": [],
      "_processing": {
        "log_file_created": "2026-07-15T03:56:40Z"
      }
    },
    {
      "description": "Third Reading Passed",
      "date": "2026-04-08",
      "organization_id": "~{\"classification\": \"lower\"}",
      "classification": [
        "passage"
      ],
      "related_entities": [],
      "_processing": {
        "log_file_created": "2026-07-15T03:56:40Z"
      }
    },
    {
      "description": "Returned Passed",
      "date": "2026-04-08",
      "organization_id": "~{\"classification\": \"upper\"}",
      "classification": [],
      "related_entities": [],
      "_processing": {
        "log_file_created": "2026-07-15T03:56:40Z"
      }
    },
    {
      "description": "Approved by the Governor - Chapter 562",
      "date": "2026-05-12",
      "organization_id": "~{\"classification\": \"executive\"}",
      "classification": [
        "executive-signature"
      ],
      "related_entities": [],
      "_processing": {
        "log_file_created": "2026-07-15T03:56:40Z"
      }
    }
  ],
  "sponsorships": [
    {
      "name": "President",
      "classification": "primary",
      "entity_type": "person",
      "primary": true,
      "person_id": "~{\"name\": \"President\"}",
      "organization_id": null
    },
    {
      "name": "Governor's Salary Commission",
      "classification": "primary",
      "entity_type": "person",
      "primary": true,
      "person_id": "~{\"name\": \"Governor's Salary Commission\"}",
      "organization_id": null
    }
  ],
  "related_bills": [
    {
      "identifier": "HB 607",
      "legislative_session": "2026",
      "relation_type": "companion"
    }
  ],
  "versions": [
    {
      "note": "First - Constitutional Officers - Salaries",
      "links": [
        {
          "url": "http://mgaleg.maryland.gov/2026RS/bills/sb/sb0312f.pdf",
          "media_type": "application/pdf"
        }
      ],
      "date": "",
      "classification": ""
    },
    {
      "note": "Third - Constitutional Officers - Salaries",
      "links": [
        {
          "url": "http://mgaleg.maryland.gov/2026RS/bills/sb/sb0312t.pdf",
          "media_type": "application/pdf"
        }
      ],
      "date": "",
      "classification": ""
    },
    {
      "note": "Chapter - Constitutional Officers - Salaries",
      "links": [
        {
          "url": "http://mgaleg.maryland.gov/2026RS/Chapters_noln/CH_562_sb0312t.pdf",
          "media_type": "application/pdf"
        }
      ],
      "date": "",
      "classification": ""
    }
  ],
  "documents": [
    {
      "note": "Fiscal and Policy Note",
      "links": [
        {
          "url": "http://mgaleg.maryland.gov/2026RS/fnotes/bil_0002/sb0312.pdf",
          "media_type": "application/pdf"
        }
      ],
      "date": "",
      "classification": ""
    }
  ],
  "citations": [],
  "sources": [
    {
      "url": "http://mgaleg.maryland.gov/mgawebsite/Legislation/Details/sb0312?ys=2026RS",
      "note": ""
    }
  ],
  "extras": {
    "date_effective": "October 1, 2026"
  },
  "jurisdiction": {
    "id": "ocd-jurisdiction/country:us/state:md/government",
    "name": "Maryland",
    "classification": "state",
    "division_id": "ocd-division/country:us/state:md"
  },
  "_processing": {
    "logs_latest_update": "2026-07-15T03:56:40Z",
    "text_extraction_latest_update": "2026-07-21T08:43:16.136007Z"
  }
}