{
  "legislative_session": "2026",
  "identifier": "SB0884",
  "title": "Internet Poker Authorization and Regulation Act of 2026",
  "from_organization": "~{\"classification\": \"upper\"}",
  "classification": [
    "bill"
  ],
  "subject": [],
  "abstracts": [],
  "other_titles": [],
  "other_identifiers": [
    {
      "identifier": "ocd-bill-md-2026-sb884"
    }
  ],
  "actions": [
    {
      "description": "First Reading Budget and Taxation",
      "date": "2026-02-06",
      "organization_id": "~{\"classification\": \"upper\"}",
      "classification": [
        "referral-committee"
      ],
      "related_entities": [],
      "_processing": {
        "log_file_created": "2026-07-15T03:56:40Z"
      }
    },
    {
      "description": "Hearing 3/11 at 1:00 p.m.",
      "date": "2026-02-11",
      "organization_id": "~{\"classification\": \"upper\"}",
      "classification": [],
      "related_entities": [],
      "_processing": {
        "log_file_created": "2026-07-15T03:56:40Z"
      }
    },
    {
      "description": "Hearing canceled",
      "date": "2026-03-11",
      "organization_id": "~{\"classification\": \"upper\"}",
      "classification": [],
      "related_entities": [],
      "_processing": {
        "log_file_created": "2026-07-15T03:56:40Z"
      }
    },
    {
      "description": "Withdrawn by Sponsor",
      "date": "2026-03-13",
      "organization_id": "~{\"classification\": \"upper\"}",
      "classification": [
        "withdrawal"
      ],
      "related_entities": [],
      "_processing": {
        "log_file_created": "2026-07-15T03:56:40Z"
      }
    }
  ],
  "sponsorships": [
    {
      "name": "Watson",
      "classification": "primary",
      "entity_type": "person",
      "primary": true,
      "person_id": "~{\"chamber\": \"upper\", \"name\": \"Watson\"}",
      "organization_id": null
    }
  ],
  "related_bills": [],
  "versions": [
    {
      "note": "First - Internet Poker Authorization and Regulation Act of 2026",
      "links": [
        {
          "url": "http://mgaleg.maryland.gov/2026RS/bills/sb/sb0884f.pdf",
          "media_type": "application/pdf"
        }
      ],
      "date": "",
      "classification": ""
    }
  ],
  "documents": [
    {
      "note": "Fiscal and Policy Note",
      "links": [
        {
          "url": "http://mgaleg.maryland.gov/2026RS/fnotes/bil_0004/sb0884.pdf",
          "media_type": "application/pdf"
        }
      ],
      "date": "",
      "classification": ""
    }
  ],
  "citations": [],
  "sources": [
    {
      "url": "http://mgaleg.maryland.gov/mgawebsite/Legislation/Details/sb0884?ys=2026RS",
      "note": ""
    }
  ],
  "extras": {
    "date_effective": "July 1, 2026"
  },
  "jurisdiction": {
    "id": "ocd-jurisdiction/country:us/state:md/government",
    "name": "Maryland",
    "classification": "state",
    "division_id": "ocd-division/country:us/state:md"
  },
  "_processing": {
    "logs_latest_update": "2026-07-15T03:56:40Z"
  }
}