{
  "legislative_session": "2026",
  "identifier": "SB0947",
  "title": "Maryland Transit Administration Reform Act",
  "from_organization": "~{\"classification\": \"upper\"}",
  "classification": [
    "bill"
  ],
  "subject": [],
  "abstracts": [],
  "other_titles": [],
  "other_identifiers": [
    {
      "identifier": "ocd-bill-md-2026-sb947"
    }
  ],
  "actions": [
    {
      "description": "First Reading Finance and Budget and Taxation",
      "date": "2026-02-06",
      "organization_id": "~{\"classification\": \"upper\"}",
      "classification": [
        "referral-committee"
      ],
      "related_entities": [],
      "_processing": {
        "log_file_created": "2026-07-15T03:56:42Z"
      }
    },
    {
      "description": "Hearing 2/25 at 1:00 p.m. (Finance)",
      "date": "2026-02-11",
      "organization_id": "~{\"classification\": \"upper\"}",
      "classification": [],
      "related_entities": [],
      "_processing": {
        "log_file_created": "2026-07-15T03:56:42Z"
      }
    },
    {
      "description": "Hearing canceled (Finance)",
      "date": "2026-02-11",
      "organization_id": "~{\"classification\": \"upper\"}",
      "classification": [],
      "related_entities": [],
      "_processing": {
        "log_file_created": "2026-07-15T03:56:42Z"
      }
    },
    {
      "description": "Hearing 3/06 at 1:00 p.m. (Finance)",
      "date": "2026-02-12",
      "organization_id": "~{\"classification\": \"upper\"}",
      "classification": [],
      "related_entities": [],
      "_processing": {
        "log_file_created": "2026-07-15T03:56:42Z"
      }
    },
    {
      "description": "Hearing canceled (Finance)",
      "date": "2026-03-02",
      "organization_id": "~{\"classification\": \"upper\"}",
      "classification": [],
      "related_entities": [],
      "_processing": {
        "log_file_created": "2026-07-15T03:56:42Z"
      }
    },
    {
      "description": "Hearing 3/06 at 12:00 p.m. (Finance)",
      "date": "2026-03-02",
      "organization_id": "~{\"classification\": \"upper\"}",
      "classification": [],
      "related_entities": [],
      "_processing": {
        "log_file_created": "2026-07-15T03:56:42Z"
      }
    },
    {
      "description": "Favorable with Amendments Report by Finance",
      "date": "2026-03-23",
      "organization_id": "~{\"classification\": \"upper\"}",
      "classification": [
        "committee-passage-favorable"
      ],
      "related_entities": [],
      "_processing": {
        "log_file_created": "2026-07-15T03:56:42Z"
      }
    },
    {
      "description": "Favorable with Amendments {",
      "date": "2026-03-23",
      "organization_id": "~{\"classification\": \"upper\"}",
      "classification": [
        "committee-passage-favorable"
      ],
      "related_entities": [],
      "_processing": {
        "log_file_created": "2026-07-15T03:56:42Z"
      }
    },
    {
      "description": "Second Reading Passed with Amendments",
      "date": "2026-03-23",
      "organization_id": "~{\"classification\": \"upper\"}",
      "classification": [],
      "related_entities": [],
      "_processing": {
        "log_file_created": "2026-07-15T03:56:42Z"
      }
    },
    {
      "description": "Third Reading Passed",
      "date": "2026-03-24",
      "organization_id": "~{\"classification\": \"upper\"}",
      "classification": [
        "passage"
      ],
      "related_entities": [],
      "_processing": {
        "log_file_created": "2026-07-15T03:56:42Z"
      }
    },
    {
      "description": "Referred Rules and Executive Nominations",
      "date": "2026-03-25",
      "organization_id": "~{\"classification\": \"lower\"}",
      "classification": [
        "referral-committee"
      ],
      "related_entities": [],
      "_processing": {
        "log_file_created": "2026-07-15T03:56:42Z"
      }
    },
    {
      "description": "Rereferred to Environment and Transportation",
      "date": "2026-04-06",
      "organization_id": "~{\"classification\": \"lower\"}",
      "classification": [],
      "related_entities": [],
      "_processing": {
        "log_file_created": "2026-07-15T03:56:42Z"
      }
    },
    {
      "description": "Favorable with Amendments Report by Environment and Transportation",
      "date": "2026-04-09",
      "organization_id": "~{\"classification\": \"lower\"}",
      "classification": [
        "committee-passage-favorable"
      ],
      "related_entities": [],
      "_processing": {
        "log_file_created": "2026-07-15T03:56:42Z"
      }
    },
    {
      "description": "Favorable with Amendments {",
      "date": "2026-04-10",
      "organization_id": "~{\"classification\": \"lower\"}",
      "classification": [
        "committee-passage-favorable"
      ],
      "related_entities": [],
      "_processing": {
        "log_file_created": "2026-07-15T03:56:42Z"
      }
    },
    {
      "description": "Second Reading Passed with Amendments",
      "date": "2026-04-10",
      "organization_id": "~{\"classification\": \"lower\"}",
      "classification": [],
      "related_entities": [],
      "_processing": {
        "log_file_created": "2026-07-15T03:56:42Z"
      }
    },
    {
      "description": "Third Reading Passed",
      "date": "2026-04-13",
      "organization_id": "~{\"classification\": \"lower\"}",
      "classification": [
        "passage"
      ],
      "related_entities": [],
      "_processing": {
        "log_file_created": "2026-07-15T03:56:42Z"
      }
    },
    {
      "description": "Senate Concurs House Amendments",
      "date": "2026-04-13",
      "organization_id": "~{\"classification\": \"upper\"}",
      "classification": [],
      "related_entities": [],
      "_processing": {
        "log_file_created": "2026-07-15T03:56:42Z"
      }
    },
    {
      "description": "Third Reading Passed",
      "date": "2026-04-13",
      "organization_id": "~{\"classification\": \"upper\"}",
      "classification": [
        "passage"
      ],
      "related_entities": [],
      "_processing": {
        "log_file_created": "2026-07-15T03:56:42Z"
      }
    },
    {
      "description": "Passed Enrolled",
      "date": "2026-04-13",
      "organization_id": "~{\"classification\": \"upper\"}",
      "classification": [],
      "related_entities": [],
      "_processing": {
        "log_file_created": "2026-07-15T03:56:42Z"
      }
    },
    {
      "description": "Approved by the Governor - Chapter 419",
      "date": "2026-05-12",
      "organization_id": "~{\"classification\": \"executive\"}",
      "classification": [
        "executive-signature"
      ],
      "related_entities": [],
      "_processing": {
        "log_file_created": "2026-07-15T03:56:42Z"
      }
    }
  ],
  "sponsorships": [
    {
      "name": "McCray",
      "classification": "primary",
      "entity_type": "person",
      "primary": true,
      "person_id": "~{\"chamber\": \"upper\", \"name\": \"McCray\"}",
      "organization_id": null
    }
  ],
  "related_bills": [
    {
      "identifier": "HB 1081",
      "legislative_session": "2026",
      "relation_type": "companion"
    }
  ],
  "versions": [
    {
      "note": "First - Maryland Transit Administration Reform Act",
      "links": [
        {
          "url": "http://mgaleg.maryland.gov/2026RS/bills/sb/sb0947f.pdf",
          "media_type": "application/pdf"
        }
      ],
      "date": "",
      "classification": ""
    },
    {
      "note": "Third - Maryland Transit Administration Reform Act",
      "links": [
        {
          "url": "http://mgaleg.maryland.gov/2026RS/bills/sb/sb0947t.pdf",
          "media_type": "application/pdf"
        }
      ],
      "date": "",
      "classification": ""
    },
    {
      "note": "Enrolled - Maryland Transit Administration Reform Act",
      "links": [
        {
          "url": "http://mgaleg.maryland.gov/2026RS/bills/sb/sb0947e.pdf",
          "media_type": "application/pdf"
        }
      ],
      "date": "",
      "classification": ""
    },
    {
      "note": "Chapter - Maryland Transit Administration Reform Act",
      "links": [
        {
          "url": "http://mgaleg.maryland.gov/2026RS/Chapters_noln/CH_419_sb0947e.pdf",
          "media_type": "application/pdf"
        }
      ],
      "date": "",
      "classification": ""
    }
  ],
  "documents": [
    {
      "note": "Fiscal and Policy Note (Revised)",
      "links": [
        {
          "url": "http://mgaleg.maryland.gov/2026RS/fnotes/bil_0007/sb0947.pdf",
          "media_type": "application/pdf"
        }
      ],
      "date": "",
      "classification": ""
    }
  ],
  "citations": [],
  "sources": [
    {
      "url": "http://mgaleg.maryland.gov/mgawebsite/Legislation/Details/sb0947?ys=2026RS",
      "note": ""
    }
  ],
  "extras": {
    "date_effective": "October 1, 2026"
  },
  "jurisdiction": {
    "id": "ocd-jurisdiction/country:us/state:md/government",
    "name": "Maryland",
    "classification": "state",
    "division_id": "ocd-division/country:us/state:md"
  },
  "_processing": {
    "logs_latest_update": "2026-07-15T03:56:42Z"
  }
}