{
  "legislative_session": "2026",
  "identifier": "SB0959",
  "title": "Carroll County - Alcoholic Beverages - Class 1 Distillery On-Premises Consumption Permit",
  "from_organization": "~{\"classification\": \"upper\"}",
  "classification": [
    "bill"
  ],
  "subject": [],
  "abstracts": [],
  "other_titles": [],
  "other_identifiers": [
    {
      "identifier": "ocd-bill-md-2026-sb959"
    }
  ],
  "actions": [
    {
      "description": "First Reading Senate Rules",
      "date": "2026-02-10",
      "organization_id": "~{\"classification\": \"upper\"}",
      "classification": [
        "referral-committee"
      ],
      "related_entities": [],
      "_processing": {
        "log_file_created": "2026-07-15T03:56:40Z"
      }
    }
  ],
  "sponsorships": [
    {
      "name": "Carroll County Senators",
      "classification": "primary",
      "entity_type": "person",
      "primary": true,
      "person_id": "~{\"name\": \"Carroll County Senators\"}",
      "organization_id": null
    }
  ],
  "related_bills": [
    {
      "identifier": "HB 1526",
      "legislative_session": "2026",
      "relation_type": "companion"
    }
  ],
  "versions": [
    {
      "note": "First - Carroll County - Alcoholic Beverages - Class 1 Distillery On-Premises Consumption Permit",
      "links": [
        {
          "url": "http://mgaleg.maryland.gov/2026RS/bills/sb/sb0959f.pdf",
          "media_type": "application/pdf"
        }
      ],
      "date": "",
      "classification": ""
    }
  ],
  "documents": [],
  "citations": [],
  "sources": [
    {
      "url": "http://mgaleg.maryland.gov/mgawebsite/Legislation/Details/sb0959?ys=2026RS",
      "note": ""
    }
  ],
  "extras": {
    "date_effective": "July 1, 2026"
  },
  "jurisdiction": {
    "id": "ocd-jurisdiction/country:us/state:md/government",
    "name": "Maryland",
    "classification": "state",
    "division_id": "ocd-division/country:us/state:md"
  },
  "_processing": {
    "logs_latest_update": "2026-07-15T03:56:40Z"
  }
}